DS_shorts_erivetna87/__init__.py
DS_shorts_erivetna87/df_utils.py
DS_shorts_erivetna87-0.1.1.dist-info/LICENSE
DS_shorts_erivetna87-0.1.1.dist-info/METADATA
DS_shorts_erivetna87-0.1.1.dist-info/WHEEL
DS_shorts_erivetna87-0.1.1.dist-info/top_level.txt
DS_shorts_erivetna87-0.1.1.dist-info/RECORD
